Pyro4/__init__.py
Pyro4/configuration.py
Pyro4/constants.py
Pyro4/core.py
Pyro4/errors.py
Pyro4/futures.py
Pyro4/message.py
Pyro4/naming.py
Pyro4/naming_storage.py
Pyro4/nsc.py
Pyro4/socketutil.py
Pyro4/util.py
Pyro4/socketserver/__init__.py
Pyro4/socketserver/existingconnectionserver.py
Pyro4/socketserver/multiplexserver.py
Pyro4/socketserver/threadpool.py
Pyro4/socketserver/threadpoolserver.py
Pyro4/test/__init__.py
Pyro4/test/echoserver.py
Pyro4/utils/__init__.py
Pyro4/utils/flame.py
Pyro4/utils/flameserver.py
Pyro4/utils/httpgateway.py
Pyro4-4.81.dist-info/LICENSE
Pyro4-4.81.dist-info/METADATA
Pyro4-4.81.dist-info/WHEEL
Pyro4-4.81.dist-info/entry_points.txt
Pyro4-4.81.dist-info/top_level.txt
Pyro4-4.81.dist-info/RECORD
