Metadata-Version: 2.1
Name: Pyro4
Version: 4.81
Summary: distributed object middleware for Python (RPC)
Home-page: http://pyro4.readthedocs.io
Author: Irmen de Jong
Author-email: irmen@razorvine.net
License: MIT
Keywords: distributed objects,RPC,remote method call,IPC
Platform: any
Classifier: Development Status :: 5 - Production/Stable
Classifier: Development Status :: 6 - Mature
Classifier: Intended Audience :: Developers
Classifier: License :: OSI Approved :: MIT License
Classifier: Natural Language :: English
Classifier: Natural Language :: Dutch
Classifier: Operating System :: OS Independent
Classifier: Programming Language :: Python
Classifier: Programming Language :: Python :: 2.7
Classifier: Programming Language :: Python :: 3.5
Classifier: Programming Language :: Python :: 3.6
Classifier: Programming Language :: Python :: 3.7
Classifier: Programming Language :: Python :: 3.8
Classifier: Programming Language :: Python :: 3.9
Classifier: Topic :: Software Development :: Object Brokering
Classifier: Topic :: System :: Distributed Computing
Classifier: Topic :: System :: Networking
Requires: serpent
License-File: LICENSE
